{
    "title": "EUROVISION 2021-drejtp\u00ebrdrejt",
    "text": "EUROVISION 2021-drejtp\u00ebrdrejt\nEUROVISION 2021-drejtp\u00ebrdrejt\nNgjarje muzikore, Ahoy, Rotterdam, Netherlands, 2021. Edicioni i 65-t\u00eb i Festivalit Europian t\u00eb K\u00ebng\u00ebs-Ngjarja m\u00eb e madhe muzikore e vitit hap siparin nga Rotterdami i Holland\u00ebs, n\u00ebn moton\"Open Up\". Sonte, 16 shtete konkurojn\u00eb p\u00ebr n\u00eb finale, nd\u00ebrkoh\u00eb q\u00eb p\u00ebrfaq\u00ebsuesja jon\u00eb, Anxhela Peristeri do t\u00eb k\u00ebndoj\u00eb n\u00eb gjysm\u00ebfinalen e dyt\u00eb, n\u00eb 20 Maj-n\u00eb studio me z\u00ebdh\u00ebn\u00ebsin e Eurovision p\u00ebr Shqip\u00ebrin\u00eb, Andri Xhahu-dpd me RTSH 1 HD",
    "original_url": "https://radio.rtsh.al/programet/eurovision-2021-drejtperdrejt-d123900b-4a02-4ab1-96d1-7985bc9a8970",
    "wayback_url": "https://web.archive.org/web/20210518030447/https://radio.rtsh.al/programet/eurovision-2021-drejtperdrejt-d123900b-4a02-4ab1-96d1-7985bc9a8970",
    "a_id": "Q50729731-83",
    "coref": [
        [
            [
                0
            ],
            [
                5
            ],
            [
                84
            ]
        ]
    ],
    "id_token": [
        "EUROVISION",
        "2021",
        "-",
        "drejtp\u00ebrdrejt",
        "\n",
        "EUROVISION",
        "2021",
        "-",
        "drejtp\u00ebrdrejt",
        "\n",
        "Ngjarje",
        "muzikore",
        ",",
        "Ahoy",
        ",",
        "Rotterdam",
        ",",
        "Netherlands",
        ",",
        "2021",
        ".",
        "Edicioni",
        "i",
        "65",
        "-",
        "t\u00eb",
        "i",
        "Festivalit",
        "Europian",
        "t\u00eb",
        "K\u00ebng\u00ebs",
        "-",
        "Ngjarja",
        "m\u00eb",
        "e",
        "madhe",
        "muzikore",
        "e",
        "vitit",
        "hap",
        "siparin",
        "nga",
        "Rotterdami",
        "i",
        "Holland\u00ebs",
        ",",
        "n\u00ebn",
        "moton\"Open",
        "Up",
        "\"",
        ".",
        "Sonte",
        ",",
        "16",
        "shtete",
        "konkurojn\u00eb",
        "p\u00ebr",
        "n\u00eb",
        "finale",
        ",",
        "nd\u00ebrkoh\u00eb",
        "q\u00eb",
        "p\u00ebrfaq\u00ebsuesja",
        "jon\u00eb",
        ",",
        "Anxhela",
        "Peristeri",
        "do",
        "t\u00eb",
        "k\u00ebndoj\u00eb",
        "n\u00eb",
        "gjysm\u00ebfinalen",
        "e",
        "dyt\u00eb",
        ",",
        "n\u00eb",
        "20",
        "Maj",
        "-",
        "n\u00eb",
        "studio",
        "me",
        "z\u00ebdh\u00ebn\u00ebsin",
        "e",
        "Eurovision",
        "p\u00ebr",
        "Shqip\u00ebrin\u00eb",
        ",",
        "Andri",
        "Xhahu",
        "-",
        "dpd",
        "me",
        "RTSH",
        "1",
        "HD"
    ],
    "id_token_offset": [
        {
            "start": 0,
            "end": 10
        },
        {
            "start": 11,
            "end": 15
        },
        {
            "start": 15,
            "end": 16
        },
        {
            "start": 16,
            "end": 29
        },
        {
            "start": 29,
            "end": 30
        },
        {
            "start": 30,
            "end": 40
        },
        {
            "start": 41,
            "end": 45
        },
        {
            "start": 45,
            "end": 46
        },
        {
            "start": 46,
            "end": 59
        },
        {
            "start": 59,
            "end": 60
        },
        {
            "start": 60,
            "end": 67
        },
        {
            "start": 68,
            "end": 76
        },
        {
            "start": 76,
            "end": 77
        },
        {
            "start": 78,
            "end": 82
        },
        {
            "start": 82,
            "end": 83
        },
        {
            "start": 84,
            "end": 93
        },
        {
            "start": 93,
            "end": 94
        },
        {
            "start": 95,
            "end": 106
        },
        {
            "start": 106,
            "end": 107
        },
        {
            "start": 108,
            "end": 112
        },
        {
            "start": 112,
            "end": 113
        },
        {
            "start": 114,
            "end": 122
        },
        {
            "start": 123,
            "end": 124
        },
        {
            "start": 125,
            "end": 127
        },
        {
            "start": 127,
            "end": 128
        },
        {
            "start": 128,
            "end": 130
        },
        {
            "start": 131,
            "end": 132
        },
        {
            "start": 133,
            "end": 143
        },
        {
            "start": 144,
            "end": 152
        },
        {
            "start": 153,
            "end": 155
        },
        {
            "start": 156,
            "end": 162
        },
        {
            "start": 162,
            "end": 163
        },
        {
            "start": 163,
            "end": 170
        },
        {
            "start": 171,
            "end": 173
        },
        {
            "start": 174,
            "end": 175
        },
        {
            "start": 176,
            "end": 181
        },
        {
            "start": 182,
            "end": 190
        },
        {
            "start": 191,
            "end": 192
        },
        {
            "start": 193,
            "end": 198
        },
        {
            "start": 199,
            "end": 202
        },
        {
            "start": 203,
            "end": 210
        },
        {
            "start": 211,
            "end": 214
        },
        {
            "start": 215,
            "end": 225
        },
        {
            "start": 226,
            "end": 227
        },
        {
            "start": 228,
            "end": 237
        },
        {
            "start": 237,
            "end": 238
        },
        {
            "start": 239,
            "end": 242
        },
        {
            "start": 243,
            "end": 253
        },
        {
            "start": 254,
            "end": 256
        },
        {
            "start": 256,
            "end": 257
        },
        {
            "start": 257,
            "end": 258
        },
        {
            "start": 259,
            "end": 264
        },
        {
            "start": 264,
            "end": 265
        },
        {
            "start": 266,
            "end": 268
        },
        {
            "start": 269,
            "end": 275
        },
        {
            "start": 276,
            "end": 286
        },
        {
            "start": 287,
            "end": 290
        },
        {
            "start": 291,
            "end": 293
        },
        {
            "start": 294,
            "end": 300
        },
        {
            "start": 300,
            "end": 301
        },
        {
            "start": 302,
            "end": 310
        },
        {
            "start": 311,
            "end": 313
        },
        {
            "start": 314,
            "end": 327
        },
        {
            "start": 328,
            "end": 332
        },
        {
            "start": 332,
            "end": 333
        },
        {
            "start": 334,
            "end": 341
        },
        {
            "start": 342,
            "end": 351
        },
        {
            "start": 352,
            "end": 354
        },
        {
            "start": 355,
            "end": 357
        },
        {
            "start": 358,
            "end": 365
        },
        {
            "start": 366,
            "end": 368
        },
        {
            "start": 369,
            "end": 382
        },
        {
            "start": 383,
            "end": 384
        },
        {
            "start": 385,
            "end": 389
        },
        {
            "start": 389,
            "end": 390
        },
        {
            "start": 391,
            "end": 393
        },
        {
            "start": 394,
            "end": 396
        },
        {
            "start": 397,
            "end": 400
        },
        {
            "start": 400,
            "end": 401
        },
        {
            "start": 401,
            "end": 403
        },
        {
            "start": 404,
            "end": 410
        },
        {
            "start": 411,
            "end": 413
        },
        {
            "start": 414,
            "end": 424
        },
        {
            "start": 425,
            "end": 426
        },
        {
            "start": 427,
            "end": 437
        },
        {
            "start": 438,
            "end": 441
        },
        {
            "start": 442,
            "end": 452
        },
        {
            "start": 452,
            "end": 453
        },
        {
            "start": 454,
            "end": 459
        },
        {
            "start": 460,
            "end": 465
        },
        {
            "start": 465,
            "end": 466
        },
        {
            "start": 466,
            "end": 469
        },
        {
            "start": 470,
            "end": 472
        },
        {
            "start": 473,
            "end": 477
        },
        {
            "start": 478,
            "end": 479
        },
        {
            "start": 480,
            "end": 482
        }
    ],
    "coref_text": [
        {
            "EUROVISION": [
                [
                    0
                ],
                [
                    5
                ]
            ],
            "Eurovision": [
                [
                    84
                ]
            ]
        }
    ]
}